reelog/__init__.py
reelog/formatter.py
reelog/handler.py
reelog/output.py
reelog/utils.py
reelog-1.7.1.dist-info/METADATA
reelog-1.7.1.dist-info/RECORD
reelog-1.7.1.dist-info/WHEEL
reelog-1.7.1.dist-info/top_level.txt
