Metadata-Version: 2.1
Name: reelog
Version: 1.7.1
Summary: python log best practice.
Home-page: UNKNOWN
Author: Sam Rui
Author-email: samrui0129@gmail.com
License: Apache License
Platform: UNKNOWN
Classifier: License :: OSI Approved :: Apache Software License
Classifier: Programming Language :: Python
Classifier: Programming Language :: Python :: 2
Classifier: Programming Language :: Python :: 3
Classifier: Programming Language :: Python :: Implementation :: CPython
Requires-Python: >=2.7.0
